setup.py
flask_authjwt/__init__.py
flask_authjwt/application.py
flask_authjwt/authentication_types.py
flask_authjwt/caching.py
flask_authjwt/helpers.py
flask_authjwt/models.py
flask_authjwt.egg-info/PKG-INFO
flask_authjwt.egg-info/SOURCES.txt
flask_authjwt.egg-info/dependency_links.txt
flask_authjwt.egg-info/not-zip-safe
flask_authjwt.egg-info/requires.txt
flask_authjwt.egg-info/top_level.txt