Metadata-Version: 1.0
Name: flask-authjwt
Version: 0.1.1
Summary: Module to secure flask endpoints in appengine using jwt token.
Home-page: https://github.laureate.net/Laureate/flask_authjwt
Author: Handerson Contreras
Author-email: handerson.contreras@gmail.com
License: MIT
Platform: UNKNOWN
